pymultitor.py
PyMultitor-4.1.0.dist-info/LICENSE.md
PyMultitor-4.1.0.dist-info/METADATA
PyMultitor-4.1.0.dist-info/WHEEL
PyMultitor-4.1.0.dist-info/entry_points.txt
PyMultitor-4.1.0.dist-info/top_level.txt
PyMultitor-4.1.0.dist-info/RECORD
