Metadata-Version: 2.1
Name: PyMultitor
Version: 4.1.0
Summary: PyMultitor - Never Stop Even If Your IP Dropped.
Home-page: https://github.com/realgam3/pymultitor
Author: Tomer Zait (realgam3)
Author-email: realgam3@gmail.com
License: GPLv3
Project-URL: Source, https://github.com/realgam3/pymultitor
Platform: any
Classifier: Environment :: Console
Classifier: Development Status :: 5 - Production/Stable
Classifier: Intended Audience :: Developers
Classifier: Intended Audience :: Science/Research
Classifier: License :: OSI Approved :: GNU General Public License v3 (GPLv3)
Classifier: Natural Language :: English
Classifier: Operating System :: OS Independent
Classifier: Programming Language :: Python :: 3.10
Classifier: Programming Language :: Python :: 3.11
Classifier: Programming Language :: Python :: 3.12
Classifier: Programming Language :: Python :: 3 :: Only
Classifier: Topic :: Security
Classifier: Topic :: Internet
Classifier: Topic :: Internet :: WWW/HTTP
Classifier: Topic :: Internet :: Proxy Servers
Classifier: Topic :: Software Development :: Testing
Classifier: Topic :: Software Development :: Libraries :: Python Modules
Requires-Python: >=3.10
License-File: LICENSE.md
Requires-Dist: stem>=1.8.2
Requires-Dist: mitmproxy>=10.1.6
Requires-Dist: requests[socks]>=2.31.0
